Workbook

Sheet Inputs
A1: ILLUSTRATIVE ONLY - NOT LIVE DATA
A2: Start month | B2: =DATE(2026,11,1)
A3: Starting partners | B3: 100
A4: New partners per month | B4: 5
A5: Monthly partner churn | B5: 0.02
A6: Monthly GMV per active partner | B6: 1000
A7: Monthly productivity growth | B7: 0.01
A8: Refund rate | B8: 0.05
A9: Take rate on net GMV | B9: 0.12
A10: Variable cost / net GMV | B10: 0.03
A11: Fixed monthly operating cost | B11: 2000
A12: Monthly program investment | B12: 1000
A13: Counterfactual GMV multiplier | B13: 0.8
A14: Counterfactual take rate | B14: 0.1
... A22: Minimum beginning partners for alerts | B22: 30

Sheet Base
A1: Month | B1: Date | C1: Begin partners | D1: Churn rate | E1: Exits | F1: New partners | G1: End partners | H1: Productivity | I1: Gross GMV | J1: Refunds | K1: Net GMV | L1: Take rate | M1: Net fee revenue | N1: Variable costs | O1: Contribution | P1: Fixed costs | Q1: Program cost | R1: Net operating contribution | S1: Counterfactual contribution | T1: Incremental contribution pre-program | U1: Program ROI | V1: Take rate delta | W1: Alert state
A2: 1 | B2: =EDATE(Inputs!$B$2,A2-1) | C2: =Inputs!$B$3 | D2: =MAX(0,MIN(1,Inputs!$B$5)) | E2: =C2*D2 | F2: =Inputs!$B$4 | G2: =C2-E2+F2 | H2: =Inputs!$B$6*(1+Inputs!$B$7)^(A2-1) | I2: =(C2+G2)/2*H2 | J2: =I2*Inputs!$B$8 | K2: =I2-J2 | L2: =MAX(0,MIN(1,Inputs!$B$9)) | M2: =K2*L2 | N2: =K2*Inputs!$B$10 | O2: =M2-N2 | P2: =Inputs!$B$11 | Q2: =Inputs!$B$12 | R2: =O2-P2-Q2 | S2: =K2*Inputs!$B$13*(Inputs!$B$14-Inputs!$B$10) | T2: =O2-S2 | U2: =IF(Q2=0,"",(T2-Q2)/Q2) | V2: =0 | W2: =IF(Inputs!$B$21<>1,"DATA BLOCKED",IF(C2<Inputs!$B$22,"INSUFFICIENT COHORT",IF(OR(D2>Inputs!$B$19,V2<-Inputs!$B$20),"REVIEW","OK")))
A3: 2 | B3: =EDATE(Inputs!$B$2,A3-1) | C3: =G2 | D3: =MAX(0,MIN(1,Inputs!$B$5)) | E3: =C3*D3 | F3: =Inputs!$B$4 | G3: =C3-E3+F3 | H3: =Inputs!$B$6*(1+Inputs!$B$7)^(A3-1) | I3: =(C3+G3)/2*H3 | J3: =I3*Inputs!$B$8 | K3: =I3-J3 | L3: =MAX(0,MIN(1,Inputs!$B$9)) | M3: =K3*L3 | N3: =K3*Inputs!$B$10 | O3: =M3-N3 | P3: =Inputs!$B$11 | Q3: =Inputs!$B$12 | R3: =O3-P3-Q3 | S3: =K3*Inputs!$B$13*(Inputs!$B$14-Inputs!$B$10) | T3: =O3-S3 | U3: =IF(Q3=0,"",(T3-Q3)/Q3) | V3: =L3-L2 | W3: =IF(Inputs!$B$21<>1,"DATA BLOCKED",IF(C3<Inputs!$B$22,"INSUFFICIENT COHORT",IF(OR(D3>Inputs!$B$19,V3<-Inputs!$B$20),"REVIEW","OK")))
A4: 3 | B4: =EDATE(Inputs!$B$2,A4-1) | C4: =G3 | D4: =MAX(0,MIN(1,Inputs!$B$5)) | E4: =C4*D4 | F4: =Inputs!$B$4 | G4: =C4-E4+F4 | H4: =Inputs!$B$6*(1+Inputs!$B$7)^(A4-1) | I4: =(C4+G4)/2*H4 | J4: =I4*Inputs!$B$8 | K4: =I4-J4 | L4: =MAX(0,MIN(1,Inputs!$B$9)) | M4: =K4*L4 | N4: =K4*Inputs!$B$10 | O4: =M4-N4 | P4: =Inputs!$B$11 | Q4: =Inputs!$B$12 | R4: =O4-P4-Q4 | S4: =K4*Inputs!$B$13*(Inputs!$B$14-Inputs!$B$10) | T4: =O4-S4 | U4: =IF(Q4=0,"",(T4-Q4)/Q4) | V4: =L4-L3 | W4: =IF(Inputs!$B$21<>1,"DATA BLOCKED",IF(C4<Inputs!$B$22,"INSUFFICIENT COHORT",IF(OR(D4>Inputs!$B$19,V4<-Inputs!$B$20),"REVIEW","OK")))
A5: 4 | B5: =EDATE(Inputs!$B$2,A5-1) | C5: =G4 | D5: =MAX(0,MIN(1,Inputs!$B$5)) | E5: =C5*D5 | F5: =Inputs!$B$4 | G5: =C5-E5+F5 | H5: =Inputs!$B$6*(1+Inputs!$B$7)^(A5-1) | I5: =(C5+G5)/2*H5 | J5: =I5*Inputs!$B$8 | K5: =I5-J5 | L5: =MAX(0,MIN(1,Inputs!$B$9)) | M5: =K5*L5 | N5: =K5*Inputs!$B$10 | O5: =M5-N5 | P5: =Inputs!$B$11 | Q5: =Inputs!$B$12 | R5: =O5-P5-Q5 | S5: =K5*Inputs!$B$13*(Inputs!$B$14-Inputs!$B$10) | T5: =O5-S5 | U5: =IF(Q5=0,"",(T5-Q5)/Q5) | V5: =L5-L4 | W5: =IF(Inputs!$B$21<>1,"DATA BLOCKED",IF(C5<Inputs!$B$22,"INSUFFICIENT COHORT",IF(OR(D5>Inputs!$B$19,V5<-Inputs!$B$20),"REVIEW","OK")))
A6: 5 | B6: =EDATE(Inputs!$B$2,A6-1) | C6: =G5 | D6: =MAX(0,MIN(1,Inputs!$B$5)) | E6: =C6*D6 | F6: =Inputs!$B$4 | G6: =C6-E6+F6 | H6: =Inputs!$B$6*(1+Inputs!$B$7)^(A6-1) | I6: =(C6+G6)/2*H6 | J6: =I6*Inputs!$B$8 | K6: =I6-J6 | L6: =MAX(0,MIN(1,Inputs!$B$9)) | M6: =K6*L6 | N6: =K6*Inputs!$B$10 | O6: =M6-N6 | P6: =Inputs!$B$11 | Q6: =Inputs!$B$12 | R6: =O6-P6-Q6 | S6: =K6*Inputs!$B$13*(Inputs!$B$14-Inputs!$B$10) | T6: =O6-S6 | U6: =IF(Q6=0,"",(T6-Q6)/Q6) | V6: =L6-L5 | W6: =IF(Inputs!$B$21<>1,"DATA BLOCKED",IF(C6<Inputs!$B$22,"INSUFFICIENT COHORT",IF(OR(D6>Inputs!$B$19,V6<-Inputs!$B$20),"REVIEW","OK")))
A7: 6 | B7: =EDATE(Inputs!$B$2,A7-1) | C7: =G6 | D7: =MAX(0,MIN(1,Inputs!$B$5)) | E7: =C7*D7 | F7: =Inputs!$B$4 | G7: =C7-E7+F7 | H7: =Inputs!$B$6*(1+Inputs!$B$7)^(A7-1) | I7: =(C7+G7)/2*H7 | J7: =I7*Inputs!$B$8 | K7: =I7-J7 | L7: =MAX(0,MIN(1,Inputs!$B$9)) | M7: =K7*L7 | N7: =K7*Inputs!$B$10 | O7: =M7-N7 | P7: =Inputs!$B$11 | Q7: =Inputs!$B$12 | R7: =O7-P7-Q7 | S7: =K7*Inputs!$B$13*(Inputs!$B$14-Inputs!$B$10) | T7: =O7-S7 | U7: =IF(Q7=0,"",(T7-Q7)/Q7) | V7: =L7-L6 | W7: =IF(Inputs!$B$21<>1,"DATA BLOCKED",IF(C7<Inputs!$B$22,"INSUFFICIENT COHORT",IF(OR(D7>Inputs!$B$19,V7<-Inputs!$B$20),"REVIEW","OK")))
A8: 7 | B8: =EDATE(Inputs!$B$2,A8-1) | C8: =G7 | D8: =MAX(0,MIN(1,Inputs!$B$5)) | E8: =C8*D8 | F8: =Inputs!$B$4 | G8: =C8-E8+F8 | H8: =Inputs!$B$6*(1+Inputs!$B$7)^(A8-1) | I8: =(C8+G8)/2*H8 | J8: =I8*Inputs!$B$8 | K8: =I8-J8 | L8: =MAX(0,MIN(1,Inputs!$B$9)) | M8: =K8*L8 | N8: =K8*Inputs!$B$10 | O8: =M8-N8 | P8: =Inputs!$B$11 | Q8: =Inputs!$B$12 | R8: =O8-P8-Q8 | S8: =K8*Inputs!$B$13*(Inputs!$B$14-Inputs!$B$10) | T8: =O8-S8 | U8: =IF(Q8=0,"",(T8-Q8)/Q8) | V8: =L8-L7 | W8: =IF(Inputs!$B$21<>1,"DATA BLOCKED",IF(C8<Inputs!$B$22,"INSUFFICIENT COHORT",IF(OR(D8>Inputs!$B$19,V8<-Inputs!$B$20),"REVIEW","OK")))
A9: 8 | B9: =EDATE(Inputs!$B$2,A9-1) | C9: =G8 | D9: =MAX(0,MIN(1,Inputs!$B$5)) | E9: =C9*D9 | F9: =Inputs!$B$4 | G9: =C9-E9+F9 | H9: =Inputs!$B$6*(1+Inputs!$B$7)^(A9-1) | I9: =(C9+G9)/2*H9 | J9: =I9*Inputs!$B$8 | K9: =I9-J9 | L9: =MAX(0,MIN(1,Inputs!$B$9)) | M9: =K9*L9 | N9: =K9*Inputs!$B$10 | O9: =M9-N9 | P9: =Inputs!$B$11 | Q9: =Inputs!$B$12 | R9: =O9-P9-Q9 | S9: =K9*Inputs!$B$13*(Inputs!$B$14-Inputs!$B$10) | T9: =O9-S9 | U9: =IF(Q9=0,"",(T9-Q9)/Q9) | V9: =L9-L8 | W9: =IF(Inputs!$B$21<>1,"DATA BLOCKED",IF(C9<Inputs!$B$22,"INSUFFICIENT COHORT",IF(OR(D9>Inputs!$B$19,V9<-Inputs!$B$20),"REVIEW","OK")))
A10: 9 | B10: =EDATE(Inputs!$B$2,A10-1) | C10: =G9 | D10: =MAX(0,MIN(1,Inputs!$B$5)) | E10: =C10*D10 | F10: =Inputs!$B$4 | G10: =C10-E10+F10 | H10: =Inputs!$B$6*(1+Inputs!$B$7)^(A10-1) | I10: =(C10+G10)/2*H10 | J10: =I10*Inputs!$B$8 | K10: =I10-J10 | L10: =MAX(0,MIN(1,Inputs!$B$9)) | M10: =K10*L10 | N10: =K10*Inputs!$B$10 | O10: =M10-N10 | P10: =Inputs!$B$11 | Q10: =Inputs!$B$12 | R10: =O10-P10-Q10 | S10: =K10*Inputs!$B$13*(Inputs!$B$14-Inputs!$B$10) | T10: =O10-S10 | U10: =IF(Q10=0,"",(T10-Q10)/Q10) | V10: =L10-L9 | W10: =IF(Inputs!$B$21<>1,"DATA BLOCKED",IF(C10<Inputs!$B$22,"INSUFFICIENT COHORT",IF(OR(D10>Inputs!$B$19,V10<-Inputs!$B$20),"REVIEW","OK")))
A11: 10 | B11: =EDATE(Inputs!$B$2,A11-1) | C11: =G10 | D11: =MAX(0,MIN(1,Inputs!$B$5)) | E11: =C11*D11 | F11: =Inputs!$B$4 | G11: =C11-E11+F11 | H11: =Inputs!$B$6*(1+Inputs!$B$7)^(A11-1) | I11: =(C11+G11)/2*H11 | J11: =I11*Inputs!$B$8 | K11: =I11-J11 | L11: =MAX(0,MIN(1,Inputs!$B$9)) | M11: =K11*L11 | N11: =K11*Inputs!$B$10 | O11: =M11-N11 | P11: =Inputs!$B$11 | Q11: =Inputs!$B$12 | R11: =O11-P11-Q11 | S11: =K11*Inputs!$B$13*(Inputs!$B$14-Inputs!$B$10) | T11: =O11-S11 | U11: =IF(Q11=0,"",(T11-Q11)/Q11) | V11: =L11-L10 | W11: =IF(Inputs!$B$21<>1,"DATA BLOCKED",IF(C11<Inputs!$B$22,"INSUFFICIENT COHORT",IF(OR(D11>Inputs!$B$19,V11<-Inputs!$B$20),"REVIEW","OK")))
A12: 11 | B12: =EDATE(Inputs!$B$2,A12-1) | C12: =G11 | D12: =MAX(0,MIN(1,Inputs!$B$5)) | E12: =C12*D12 | F12: =Inputs!$B$4 | G12: =C12-E12+F12 | H12: =Inputs!$B$6*(1+Inputs!$B$7)^(A12-1) | I12: =(C12+G12)/2*H12 | J12: =I12*Inputs!$B$8 | K12: =I12-J12 | L12: =MAX(0,MIN(1,Inputs!$B$9)) | M12: =K12*L12 | N12: =K12*Inputs!$B$10 | O12: =M12-N12 | P12: =Inputs!$B$11 | Q12: =Inputs!$B$12 | R12: =O12-P12-Q12 | S12: =K12*Inputs!$B$13*(Inputs!$B$14-Inputs!$B$10) | T12: =O12-S12 | U12: =IF(Q12=0,"",(T12-Q12)/Q12) | V12: =L12-L11 | W12: =IF(Inputs!$B$21<>1,"DATA BLOCKED",IF(C12<Inputs!$B$22,"INSUFFICIENT COHORT",IF(OR(D12>Inputs!$B$19,V12<-Inputs!$B$20),"REVIEW","OK")))
A13: 12 | B13: =EDATE(Inputs!$B$2,A13-1) | C13: =G12 | D13: =MAX(0,MIN(1,Inputs!$B$5)) | E13: =C13*D13 | F13: =Inputs!$B$4 | G13: =C13-E13+F13 | H13: =Inputs!$B$6*(1+Inputs!$B$7)^(A13-1) | I13: =(C13+G13)/2*H13 | J13: =I13*Inputs!$B$8 | K13: =I13-J13 | L13: =MAX(0,MIN(1,Inputs!$B$9)) | M13: =K13*L13 | N13: =K13*Inputs!$B$10 | O13: =M13-N13 | P13: =Inputs!$B$11 | Q13: =Inputs!$B$12 | R13: =O13-P13-Q13 | S13: =K13*Inputs!$B$13*(Inputs!$B$14-Inputs!$B$10) | T13: =O13-S13 | U13: =IF(Q13=0,"",(T13-Q13)/Q13) | V13: =L13-L12 | W13: =IF(Inputs!$B$21<>1,"DATA BLOCKED",IF(C13<Inputs!$B$22,"INSUFFICIENT COHORT",IF(OR(D13>Inputs!$B$19,V13<-Inputs!$B$20),"REVIEW","OK")))
A14: 13 | B14: =EDATE(Inputs!$B$2,A14-1) | C14: =G13 | D14: =MAX(0,MIN(1,Inputs!$B$5)) | E14: =C14*D14 | F14: =Inputs!$B$4 | G14: =C14-E14+F14 | H14: =Inputs!$B$6*(1+Inputs!$B$7)^(A14-1) | I14: =(C14+G14)/2*H14 | J14: =I14*Inputs!$B$8 | K14: =I14-J14 | L14: =MAX(0,MIN(1,Inputs!$B$9)) | M14: =K14*L14 | N14: =K14*Inputs!$B$10 | O14: =M14-N14 | P14: =Inputs!$B$11 | Q14: =Inputs!$B$12 | R14: =O14-P14-Q14 | S14: =K14*Inputs!$B$13*(Inputs!$B$14-Inputs!$B$10) | T14: =O14-S14 | U14: =IF(Q14=0,"",(T14-Q14)/Q14) | V14: =L14-L13 | W14: =IF(Inputs!$B$21<>1,"DATA BLOCKED",IF(C14<Inputs!$B$22,"INSUFFICIENT COHORT",IF(OR(D14>Inputs!$B$19,V14<-Inputs!$B$20),"REVIEW","OK")))
... A37: 36 | B37: =EDATE(Inputs!$B$2,A37-1) | C37: =G36 | D37: =MAX(0,MIN(1,Inputs!$B$5)) | E37: =C37*D37 | F37: =Inputs!$B$4 | G37: =C37-E37+F37 | H37: =Inputs!$B$6*(1+Inputs!$B$7)^(A37-1) | I37: =(C37+G37)/2*H37 | J37: =I37*Inputs!$B$8 | K37: =I37-J37 | L37: =MAX(0,MIN(1,Inputs!$B$9)) | M37: =K37*L37 | N37: =K37*Inputs!$B$10 | O37: =M37-N37 | P37: =Inputs!$B$11 | Q37: =Inputs!$B$12 | R37: =O37-P37-Q37 | S37: =K37*Inputs!$B$13*(Inputs!$B$14-Inputs!$B$10) | T37: =O37-S37 | U37: =IF(Q37=0,"",(T37-Q37)/Q37) | V37: =L37-L36 | W37: =IF(Inputs!$B$21<>1,"DATA BLOCKED",IF(C37<Inputs!$B$22,"INSUFFICIENT COHORT",IF(OR(D37>Inputs!$B$19,V37<-Inputs!$B$20),"REVIEW","OK")))

Sheet Scenario
A1: Month | B1: Date | C1: Begin partners | D1: Churn rate | E1: Exits | F1: New partners | G1: End partners | H1: Productivity | I1: Gross GMV | J1: Refunds | K1: Net GMV | L1: Take rate | M1: Net fee revenue | N1: Variable costs | O1: Contribution | P1: Fixed costs | Q1: Program cost | R1: Net operating contribution | S1: Counterfactual contribution | T1: Incremental contribution pre-program | U1: Program ROI | V1: Take rate delta | W1: Alert state
A2: 1 | B2: =EDATE(Inputs!$B$2,A2-1) | C2: =Inputs!$B$3 | D2: =MAX(0,MIN(1,Inputs!$B$5+Inputs!$B$16)) | E2: =C2*D2 | F2: =Inputs!$B$4 | G2: =C2-E2+F2 | H2: =Inputs!$B$6*(1+Inputs!$B$7)^(A2-1) | I2: =(C2+G2)/2*H2 | J2: =I2*Inputs!$B$8 | K2: =I2-J2 | L2: =MAX(0,MIN(1,Inputs!$B$9+Inputs!$B$15)) | M2: =K2*L2 | N2: =K2*Inputs!$B$10 | O2: =M2-N2 | P2: =Inputs!$B$11 | Q2: =Inputs!$B$12 | R2: =O2-P2-Q2 | S2: =K2*Inputs!$B$13*(Inputs!$B$14-Inputs!$B$10) | T2: =O2-S2 | U2: =IF(Q2=0,"",(T2-Q2)/Q2) | V2: =0 | W2: =IF(Inputs!$B$21<>1,"DATA BLOCKED",IF(C2<Inputs!$B$22,"INSUFFICIENT COHORT",IF(OR(D2>Inputs!$B$19,V2<-Inputs!$B$20),"REVIEW","OK")))
A3: 2 | B3: =EDATE(Inputs!$B$2,A3-1) | C3: =G2 | D3: =MAX(0,MIN(1,Inputs!$B$5+Inputs!$B$16)) | E3: =C3*D3 | F3: =Inputs!$B$4 | G3: =C3-E3+F3 | H3: =Inputs!$B$6*(1+Inputs!$B$7)^(A3-1) | I3: =(C3+G3)/2*H3 | J3: =I3*Inputs!$B$8 | K3: =I3-J3 | L3: =MAX(0,MIN(1,Inputs!$B$9+Inputs!$B$15)) | M3: =K3*L3 | N3: =K3*Inputs!$B$10 | O3: =M3-N3 | P3: =Inputs!$B$11 | Q3: =Inputs!$B$12 | R3: =O3-P3-Q3 | S3: =K3*Inputs!$B$13*(Inputs!$B$14-Inputs!$B$10) | T3: =O3-S3 | U3: =IF(Q3=0,"",(T3-Q3)/Q3) | V3: =L3-L2 | W3: =IF(Inputs!$B$21<>1,"DATA BLOCKED",IF(C3<Inputs!$B$22,"INSUFFICIENT COHORT",IF(OR(D3>Inputs!$B$19,V3<-Inputs!$B$20),"REVIEW","OK")))
A4: 3 | B4: =EDATE(Inputs!$B$2,A4-1) | C4: =G3 | D4: =MAX(0,MIN(1,Inputs!$B$5+Inputs!$B$16)) | E4: =C4*D4 | F4: =Inputs!$B$4 | G4: =C4-E4+F4 | H4: =Inputs!$B$6*(1+Inputs!$B$7)^(A4-1) | I4: =(C4+G4)/2*H4 | J4: =I4*Inputs!$B$8 | K4: =I4-J4 | L4: =MAX(0,MIN(1,Inputs!$B$9+Inputs!$B$15)) | M4: =K4*L4 | N4: =K4*Inputs!$B$10 | O4: =M4-N4 | P4: =Inputs!$B$11 | Q4: =Inputs!$B$12 | R4: =O4-P4-Q4 | S4: =K4*Inputs!$B$13*(Inputs!$B$14-Inputs!$B$10) | T4: =O4-S4 | U4: =IF(Q4=0,"",(T4-Q4)/Q4) | V4: =L4-L3 | W4: =IF(Inputs!$B$21<>1,"DATA BLOCKED",IF(C4<Inputs!$B$22,"INSUFFICIENT COHORT",IF(OR(D4>Inputs!$B$19,V4<-Inputs!$B$20),"REVIEW","OK")))
A5: 4 | B5: =EDATE(Inputs!$B$2,A5-1) | C5: =G4 | D5: =MAX(0,MIN(1,Inputs!$B$5+Inputs!$B$16)) | E5: =C5*D5 | F5: =Inputs!$B$4 | G5: =C5-E5+F5 | H5: =Inputs!$B$6*(1+Inputs!$B$7)^(A5-1) | I5: =(C5+G5)/2*H5 | J5: =I5*Inputs!$B$8 | K5: =I5-J5 | L5: =MAX(0,MIN(1,Inputs!$B$9+Inputs!$B$15)) | M5: =K5*L5 | N5: =K5*Inputs!$B$10 | O5: =M5-N5 | P5: =Inputs!$B$11 | Q5: =Inputs!$B$12 | R5: =O5-P5-Q5 | S5: =K5*Inputs!$B$13*(Inputs!$B$14-Inputs!$B$10) | T5: =O5-S5 | U5: =IF(Q5=0,"",(T5-Q5)/Q5) | V5: =L5-L4 | W5: =IF(Inputs!$B$21<>1,"DATA BLOCKED",IF(C5<Inputs!$B$22,"INSUFFICIENT COHORT",IF(OR(D5>Inputs!$B$19,V5<-Inputs!$B$20),"REVIEW","OK")))
A6: 5 | B6: =EDATE(Inputs!$B$2,A6-1) | C6: =G5 | D6: =MAX(0,MIN(1,Inputs!$B$5+Inputs!$B$16)) | E6: =C6*D6 | F6: =Inputs!$B$4 | G6: =C6-E6+F6 | H6: =Inputs!$B$6*(1+Inputs!$B$7)^(A6-1) | I6: =(C6+G6)/2*H6 | J6: =I6*Inputs!$B$8 | K6: =I6-J6 | L6: =MAX(0,MIN(1,Inputs!$B$9+Inputs!$B$15)) | M6: =K6*L6 | N6: =K6*Inputs!$B$10 | O6: =M6-N6 | P6: =Inputs!$B$11 | Q6: =Inputs!$B$12 | R6: =O6-P6-Q6 | S6: =K6*Inputs!$B$13*(Inputs!$B$14-Inputs!$B$10) | T6: =O6-S6 | U6: =IF(Q6=0,"",(T6-Q6)/Q6) | V6: =L6-L5 | W6: =IF(Inputs!$B$21<>1,"DATA BLOCKED",IF(C6<Inputs!$B$22,"INSUFFICIENT COHORT",IF(OR(D6>Inputs!$B$19,V6<-Inputs!$B$20),"REVIEW","OK")))
A7: 6 | B7: =EDATE(Inputs!$B$2,A7-1) | C7: =G6 | D7: =MAX(0,MIN(1,Inputs!$B$5+Inputs!$B$16)) | E7: =C7*D7 | F7: =Inputs!$B$4 | G7: =C7-E7+F7 | H7: =Inputs!$B$6*(1+Inputs!$B$7)^(A7-1) | I7: =(C7+G7)/2*H7 | J7: =I7*Inputs!$B$8 | K7: =I7-J7 | L7: =MAX(0,MIN(1,Inputs!$B$9+Inputs!$B$15)) | M7: =K7*L7 | N7: =K7*Inputs!$B$10 | O7: =M7-N7 | P7: =Inputs!$B$11 | Q7: =Inputs!$B$12 | R7: =O7-P7-Q7 | S7: =K7*Inputs!$B$13*(Inputs!$B$14-Inputs!$B$10) | T7: =O7-S7 | U7: =IF(Q7=0,"",(T7-Q7)/Q7) | V7: =L7-L6 | W7: =IF(Inputs!$B$21<>1,"DATA BLOCKED",IF(C7<Inputs!$B$22,"INSUFFICIENT COHORT",IF(OR(D7>Inputs!$B$19,V7<-Inputs!$B$20),"REVIEW","OK")))
A8: 7 | B8: =EDATE(Inputs!$B$2,A8-1) | C8: =G7 | D8: =MAX(0,MIN(1,Inputs!$B$5+Inputs!$B$16)) | E8: =C8*D8 | F8: =Inputs!$B$4 | G8: =C8-E8+F8 | H8: =Inputs!$B$6*(1+Inputs!$B$7)^(A8-1) | I8: =(C8+G8)/2*H8 | J8: =I8*Inputs!$B$8 | K8: =I8-J8 | L8: =MAX(0,MIN(1,Inputs!$B$9+Inputs!$B$15)) | M8: =K8*L8 | N8: =K8*Inputs!$B$10 | O8: =M8-N8 | P8: =Inputs!$B$11 | Q8: =Inputs!$B$12 | R8: =O8-P8-Q8 | S8: =K8*Inputs!$B$13*(Inputs!$B$14-Inputs!$B$10) | T8: =O8-S8 | U8: =IF(Q8=0,"",(T8-Q8)/Q8) | V8: =L8-L7 | W8: =IF(Inputs!$B$21<>1,"DATA BLOCKED",IF(C8<Inputs!$B$22,"INSUFFICIENT COHORT",IF(OR(D8>Inputs!$B$19,V8<-Inputs!$B$20),"REVIEW","OK")))
A9: 8 | B9: =EDATE(Inputs!$B$2,A9-1) | C9: =G8 | D9: =MAX(0,MIN(1,Inputs!$B$5+Inputs!$B$16)) | E9: =C9*D9 | F9: =Inputs!$B$4 | G9: =C9-E9+F9 | H9: =Inputs!$B$6*(1+Inputs!$B$7)^(A9-1) | I9: =(C9+G9)/2*H9 | J9: =I9*Inputs!$B$8 | K9: =I9-J9 | L9: =MAX(0,MIN(1,Inputs!$B$9+Inputs!$B$15)) | M9: =K9*L9 | N9: =K9*Inputs!$B$10 | O9: =M9-N9 | P9: =Inputs!$B$11 | Q9: =Inputs!$B$12 | R9: =O9-P9-Q9 | S9: =K9*Inputs!$B$13*(Inputs!$B$14-Inputs!$B$10) | T9: =O9-S9 | U9: =IF(Q9=0,"",(T9-Q9)/Q9) | V9: =L9-L8 | W9: =IF(Inputs!$B$21<>1,"DATA BLOCKED",IF(C9<Inputs!$B$22,"INSUFFICIENT COHORT",IF(OR(D9>Inputs!$B$19,V9<-Inputs!$B$20),"REVIEW","OK")))
A10: 9 | B10: =EDATE(Inputs!$B$2,A10-1) | C10: =G9 | D10: =MAX(0,MIN(1,Inputs!$B$5+Inputs!$B$16)) | E10: =C10*D10 | F10: =Inputs!$B$4 | G10: =C10-E10+F10 | H10: =Inputs!$B$6*(1+Inputs!$B$7)^(A10-1) | I10: =(C10+G10)/2*H10 | J10: =I10*Inputs!$B$8 | K10: =I10-J10 | L10: =MAX(0,MIN(1,Inputs!$B$9+Inputs!$B$15)) | M10: =K10*L10 | N10: =K10*Inputs!$B$10 | O10: =M10-N10 | P10: =Inputs!$B$11 | Q10: =Inputs!$B$12 | R10: =O10-P10-Q10 | S10: =K10*Inputs!$B$13*(Inputs!$B$14-Inputs!$B$10) | T10: =O10-S10 | U10: =IF(Q10=0,"",(T10-Q10)/Q10) | V10: =L10-L9 | W10: =IF(Inputs!$B$21<>1,"DATA BLOCKED",IF(C10<Inputs!$B$22,"INSUFFICIENT COHORT",IF(OR(D10>Inputs!$B$19,V10<-Inputs!$B$20),"REVIEW","OK")))
A11: 10 | B11: =EDATE(Inputs!$B$2,A11-1) | C11: =G10 | D11: =MAX(0,MIN(1,Inputs!$B$5+Inputs!$B$16)) | E11: =C11*D11 | F11: =Inputs!$B$4 | G11: =C11-E11+F11 | H11: =Inputs!$B$6*(1+Inputs!$B$7)^(A11-1) | I11: =(C11+G11)/2*H11 | J11: =I11*Inputs!$B$8 | K11: =I11-J11 | L11: =MAX(0,MIN(1,Inputs!$B$9+Inputs!$B$15)) | M11: =K11*L11 | N11: =K11*Inputs!$B$10 | O11: =M11-N11 | P11: =Inputs!$B$11 | Q11: =Inputs!$B$12 | R11: =O11-P11-Q11 | S11: =K11*Inputs!$B$13*(Inputs!$B$14-Inputs!$B$10) | T11: =O11-S11 | U11: =IF(Q11=0,"",(T11-Q11)/Q11) | V11: =L11-L10 | W11: =IF(Inputs!$B$21<>1,"DATA BLOCKED",IF(C11<Inputs!$B$22,"INSUFFICIENT COHORT",IF(OR(D11>Inputs!$B$19,V11<-Inputs!$B$20),"REVIEW","OK")))
A12: 11 | B12: =EDATE(Inputs!$B$2,A12-1) | C12: =G11 | D12: =MAX(0,MIN(1,Inputs!$B$5+Inputs!$B$16)) | E12: =C12*D12 | F12: =Inputs!$B$4 | G12: =C12-E12+F12 | H12: =Inputs!$B$6*(1+Inputs!$B$7)^(A12-1) | I12: =(C12+G12)/2*H12 | J12: =I12*Inputs!$B$8 | K12: =I12-J12 | L12: =MAX(0,MIN(1,Inputs!$B$9+Inputs!$B$15)) | M12: =K12*L12 | N12: =K12*Inputs!$B$10 | O12: =M12-N12 | P12: =Inputs!$B$11 | Q12: =Inputs!$B$12 | R12: =O12-P12-Q12 | S12: =K12*Inputs!$B$13*(Inputs!$B$14-Inputs!$B$10) | T12: =O12-S12 | U12: =IF(Q12=0,"",(T12-Q12)/Q12) | V12: =L12-L11 | W12: =IF(Inputs!$B$21<>1,"DATA BLOCKED",IF(C12<Inputs!$B$22,"INSUFFICIENT COHORT",IF(OR(D12>Inputs!$B$19,V12<-Inputs!$B$20),"REVIEW","OK")))
A13: 12 | B13: =EDATE(Inputs!$B$2,A13-1) | C13: =G12 | D13: =MAX(0,MIN(1,Inputs!$B$5+Inputs!$B$16)) | E13: =C13*D13 | F13: =Inputs!$B$4 | G13: =C13-E13+F13 | H13: =Inputs!$B$6*(1+Inputs!$B$7)^(A13-1) | I13: =(C13+G13)/2*H13 | J13: =I13*Inputs!$B$8 | K13: =I13-J13 | L13: =MAX(0,MIN(1,Inputs!$B$9+Inputs!$B$15)) | M13: =K13*L13 | N13: =K13*Inputs!$B$10 | O13: =M13-N13 | P13: =Inputs!$B$11 | Q13: =Inputs!$B$12 | R13: =O13-P13-Q13 | S13: =K13*Inputs!$B$13*(Inputs!$B$14-Inputs!$B$10) | T13: =O13-S13 | U13: =IF(Q13=0,"",(T13-Q13)/Q13) | V13: =L13-L12 | W13: =IF(Inputs!$B$21<>1,"DATA BLOCKED",IF(C13<Inputs!$B$22,"INSUFFICIENT COHORT",IF(OR(D13>Inputs!$B$19,V13<-Inputs!$B$20),"REVIEW","OK")))
A14: 13 | B14: =EDATE(Inputs!$B$2,A14-1) | C14: =G13 | D14: =MAX(0,MIN(1,Inputs!$B$5+Inputs!$B$16)) | E14: =C14*D14 | F14: =Inputs!$B$4 | G14: =C14-E14+F14 | H14: =Inputs!$B$6*(1+Inputs!$B$7)^(A14-1) | I14: =(C14+G14)/2*H14 | J14: =I14*Inputs!$B$8 | K14: =I14-J14 | L14: =MAX(0,MIN(1,Inputs!$B$9+Inputs!$B$15)) | M14: =K14*L14 | N14: =K14*Inputs!$B$10 | O14: =M14-N14 | P14: =Inputs!$B$11 | Q14: =Inputs!$B$12 | R14: =O14-P14-Q14 | S14: =K14*Inputs!$B$13*(Inputs!$B$14-Inputs!$B$10) | T14: =O14-S14 | U14: =IF(Q14=0,"",(T14-Q14)/Q14) | V14: =L14-L13 | W14: =IF(Inputs!$B$21<>1,"DATA BLOCKED",IF(C14<Inputs!$B$22,"INSUFFICIENT COHORT",IF(OR(D14>Inputs!$B$19,V14<-Inputs!$B$20),"REVIEW","OK")))
... A37: 36 | B37: =EDATE(Inputs!$B$2,A37-1) | C37: =G36 | D37: =MAX(0,MIN(1,Inputs!$B$5+Inputs!$B$16)) | E37: =C37*D37 | F37: =Inputs!$B$4 | G37: =C37-E37+F37 | H37: =Inputs!$B$6*(1+Inputs!$B$7)^(A37-1) | I37: =(C37+G37)/2*H37 | J37: =I37*Inputs!$B$8 | K37: =I37-J37 | L37: =MAX(0,MIN(1,Inputs!$B$9+Inputs!$B$15)) | M37: =K37*L37 | N37: =K37*Inputs!$B$10 | O37: =M37-N37 | P37: =Inputs!$B$11 | Q37: =Inputs!$B$12 | R37: =O37-P37-Q37 | S37: =K37*Inputs!$B$13*(Inputs!$B$14-Inputs!$B$10) | T37: =O37-S37 | U37: =IF(Q37=0,"",(T37-Q37)/Q37) | V37: =L37-L36 | W37: =IF(Inputs!$B$21<>1,"DATA BLOCKED",IF(C37<Inputs!$B$22,"INSUFFICIENT COHORT",IF(OR(D37>Inputs!$B$19,V37<-Inputs!$B$20),"REVIEW","OK")))

Sheet 3-Year Review
A1: Model | B1: Year | C1: Gross GMV | D1: Net GMV | E1: Net fees | F1: Contribution | G1: Program spend | H1: Net operating contribution | I1: Program ROI | J1: Revenue change vs base
A2: Base | B2: 1 | C2: =SUM(Base!I2:I13) | D2: =SUM(Base!K2:K13) | E2: =SUM(Base!M2:M13) | F2: =SUM(Base!O2:O13) | G2: =SUM(Base!Q2:Q13) | H2: =SUM(Base!R2:R13) | I2: =IF(G2=0,"",(SUM(Base!T2:T13)-G2)/G2) | J2: =E2-SUM(Base!M2:M13)
A3: Base | B3: 2 | C3: =SUM(Base!I14:I25) | D3: =SUM(Base!K14:K25) | E3: =SUM(Base!M14:M25) | F3: =SUM(Base!O14:O25) | G3: =SUM(Base!Q14:Q25) | H3: =SUM(Base!R14:R25) | I3: =IF(G3=0,"",(SUM(Base!T14:T25)-G3)/G3) | J3: =E3-SUM(Base!M14:M25)
A4: Base | B4: 3 | C4: =SUM(Base!I26:I37) | D4: =SUM(Base!K26:K37) | E4: =SUM(Base!M26:M37) | F4: =SUM(Base!O26:O37) | G4: =SUM(Base!Q26:Q37) | H4: =SUM(Base!R26:R37) | I4: =IF(G4=0,"",(SUM(Base!T26:T37)-G4)/G4) | J4: =E4-SUM(Base!M26:M37)
A5: Scenario | B5: 1 | C5: =SUM(Scenario!I2:I13) | D5: =SUM(Scenario!K2:K13) | E5: =SUM(Scenario!M2:M13) | F5: =SUM(Scenario!O2:O13) | G5: =SUM(Scenario!Q2:Q13) | H5: =SUM(Scenario!R2:R13) | I5: =IF(G5=0,"",(SUM(Scenario!T2:T13)-G5)/G5) | J5: =E5-SUM(Base!M2:M13)
A6: Scenario | B6: 2 | C6: =SUM(Scenario!I14:I25) | D6: =SUM(Scenario!K14:K25) | E6: =SUM(Scenario!M14:M25) | F6: =SUM(Scenario!O14:O25) | G6: =SUM(Scenario!Q14:Q25) | H6: =SUM(Scenario!R14:R25) | I6: =IF(G6=0,"",(SUM(Scenario!T14:T25)-G6)/G6) | J6: =E6-SUM(Base!M14:M25)
A7: Scenario | B7: 3 | C7: =SUM(Scenario!I26:I37) | D7: =SUM(Scenario!K26:K37) | E7: =SUM(Scenario!M26:M37) | F7: =SUM(Scenario!O26:O37) | G7: =SUM(Scenario!Q26:Q37) | H7: =SUM(Scenario!R26:R37) | I7: =IF(G7=0,"",(SUM(Scenario!T26:T37)-G7)/G7) | J7: =E7-SUM(Base!M26:M37)

Sheet Next Quarter
A1: Case | B1: Gross GMV | C1: Net GMV | D1: Net fees | E1: Contribution | F1: Basis
A2: Downside | B2: =SUM(Base!I2:I4)*Inputs!$B$17 | C2: =SUM(Base!K2:K4)*Inputs!$B$17 | D2: =C2*Inputs!$B$9 | E2: =D2-C2*Inputs!$B$10 | F2: Driver scenario, not fitted forecast or statistical interval
A3: Base | B3: =SUM(Base!I2:I4)*1 | C3: =SUM(Base!K2:K4)*1 | D3: =C3*Inputs!$B$9 | E3: =D3-C3*Inputs!$B$10 | F3: Driver scenario, not fitted forecast or statistical interval
A4: Upside | B4: =SUM(Base!I2:I4)*Inputs!$B$18 | C4: =SUM(Base!K2:K4)*Inputs!$B$18 | D4: =C4*Inputs!$B$9 | E4: =D4-C4*Inputs!$B$10 | F4: Driver scenario, not fitted forecast or statistical interval

Sheet Cohort Retention
A1: Acquisition month | B1: Initial size | C1: Month 1 | D1: Month 2 | E1: Month 3 | F1: Month 4 | G1: Month 5 | H1: Month 6 | I1: Month 7 | J1: Month 8 | K1: Month 9 | L1: Month 10 | M1: Month 11 | N1: Month 12 | O1: Month 13 | P1: Month 14 | Q1: Month 15 | R1: Month 16 | S1: Month 17 | T1: Month 18 | U1: Month 19 | V1: Month 20 | W1: Month 21 | X1: Month 22 | Y1: Month 23 | Z1: Month 24 | AA1: Month 25 | AB1: Month 26 | AC1: Month 27 | AD1: Month 28 | AE1: Month 29 | AF1: Month 30 | AG1: Month 31 | AH1: Month 32 | AI1: Month 33 | AJ1: Month 34 | AK1: Month 35 | AL1: Month 36
A2: 0 | B2: =Inputs!$B$3 | C2: =$B2*(1-Inputs!$B$5)^1 | D2: =$B2*(1-Inputs!$B$5)^2 | E2: =$B2*(1-Inputs!$B$5)^3 | F2: =$B2*(1-Inputs!$B$5)^4 | G2: =$B2*(1-Inputs!$B$5)^5 | H2: =$B2*(1-Inputs!$B$5)^6 | I2: =$B2*(1-Inputs!$B$5)^7 | J2: =$B2*(1-Inputs!$B$5)^8 | K2: =$B2*(1-Inputs!$B$5)^9 | L2: =$B2*(1-Inputs!$B$5)^10 | M2: =$B2*(1-Inputs!$B$5)^11 | N2: =$B2*(1-Inputs!$B$5)^12 | O2: =$B2*(1-Inputs!$B$5)^13 | P2: =$B2*(1-Inputs!$B$5)^14 | Q2: =$B2*(1-Inputs!$B$5)^15 | R2: =$B2*(1-Inputs!$B$5)^16 | S2: =$B2*(1-Inputs!$B$5)^17 | T2: =$B2*(1-Inputs!$B$5)^18 | U2: =$B2*(1-Inputs!$B$5)^19 | V2: =$B2*(1-Inputs!$B$5)^20 | W2: =$B2*(1-Inputs!$B$5)^21 | X2: =$B2*(1-Inputs!$B$5)^22 | Y2: =$B2*(1-Inputs!$B$5)^23 | Z2: =$B2*(1-Inputs!$B$5)^24 | AA2: =$B2*(1-Inputs!$B$5)^25 | AB2: =$B2*(1-Inputs!$B$5)^26 | AC2: =$B2*(1-Inputs!$B$5)^27 | AD2: =$B2*(1-Inputs!$B$5)^28 | AE2: =$B2*(1-Inputs!$B$5)^29 | AF2: =$B2*(1-Inputs!$B$5)^30 | AG2: =$B2*(1-Inputs!$B$5)^31 | AH2: =$B2*(1-Inputs!$B$5)^32 | AI2: =$B2*(1-Inputs!$B$5)^33 | AJ2: =$B2*(1-Inputs!$B$5)^34 | AK2: =$B2*(1-Inputs!$B$5)^35 | AL2: =$B2*(1-Inputs!$B$5)^36
A3: 1 | B3: =Inputs!$B$4 | C3: =$B3*(1-Inputs!$B$5)^0 | D3: =$B3*(1-Inputs!$B$5)^1 | E3: =$B3*(1-Inputs!$B$5)^2 | F3: =$B3*(1-Inputs!$B$5)^3 | G3: =$B3*(1-Inputs!$B$5)^4 | H3: =$B3*(1-Inputs!$B$5)^5 | I3: =$B3*(1-Inputs!$B$5)^6 | J3: =$B3*(1-Inputs!$B$5)^7 | K3: =$B3*(1-Inputs!$B$5)^8 | L3: =$B3*(1-Inputs!$B$5)^9 | M3: =$B3*(1-Inputs!$B$5)^10 | N3: =$B3*(1-Inputs!$B$5)^11 | O3: =$B3*(1-Inputs!$B$5)^12 | P3: =$B3*(1-Inputs!$B$5)^13 | Q3: =$B3*(1-Inputs!$B$5)^14 | R3: =$B3*(1-Inputs!$B$5)^15 | S3: =$B3*(1-Inputs!$B$5)^16 | T3: =$B3*(1-Inputs!$B$5)^17 | U3: =$B3*(1-Inputs!$B$5)^18 | V3: =$B3*(1-Inputs!$B$5)^19 | W3: =$B3*(1-Inputs!$B$5)^20 | X3: =$B3*(1-Inputs!$B$5)^21 | Y3: =$B3*(1-Inputs!$B$5)^22 | Z3: =$B3*(1-Inputs!$B$5)^23 | AA3: =$B3*(1-Inputs!$B$5)^24 | AB3: =$B3*(1-Inputs!$B$5)^25 | AC3: =$B3*(1-Inputs!$B$5)^26 | AD3: =$B3*(1-Inputs!$B$5)^27 | AE3: =$B3*(1-Inputs!$B$5)^28 | AF3: =$B3*(1-Inputs!$B$5)^29 | AG3: =$B3*(1-Inputs!$B$5)^30 | AH3: =$B3*(1-Inputs!$B$5)^31 | AI3: =$B3*(1-Inputs!$B$5)^32 | AJ3: =$B3*(1-Inputs!$B$5)^33 | AK3: =$B3*(1-Inputs!$B$5)^34 | AL3: =$B3*(1-Inputs!$B$5)^35
A4: 2 | B4: =Inputs!$B$4 | C4: =0 | D4: =$B4*(1-Inputs!$B$5)^0 | E4: =$B4*(1-Inputs!$B$5)^1 | F4: =$B4*(1-Inputs!$B$5)^2 | G4: =$B4*(1-Inputs!$B$5)^3 | H4: =$B4*(1-Inputs!$B$5)^4 | I4: =$B4*(1-Inputs!$B$5)^5 | J4: =$B4*(1-Inputs!$B$5)^6 | K4: =$B4*(1-Inputs!$B$5)^7 | L4: =$B4*(1-Inputs!$B$5)^8 | M4: =$B4*(1-Inputs!$B$5)^9 | N4: =$B4*(1-Inputs!$B$5)^10 | O4: =$B4*(1-Inputs!$B$5)^11 | P4: =$B4*(1-Inputs!$B$5)^12 | Q4: =$B4*(1-Inputs!$B$5)^13 | R4: =$B4*(1-Inputs!$B$5)^14 | S4: =$B4*(1-Inputs!$B$5)^15 | T4: =$B4*(1-Inputs!$B$5)^16 | U4: =$B4*(1-Inputs!$B$5)^17 | V4: =$B4*(1-Inputs!$B$5)^18 | W4: =$B4*(1-Inputs!$B$5)^19 | X4: =$B4*(1-Inputs!$B$5)^20 | Y4: =$B4*(1-Inputs!$B$5)^21 | Z4: =$B4*(1-Inputs!$B$5)^22 | AA4: =$B4*(1-Inputs!$B$5)^23 | AB4: =$B4*(1-Inputs!$B$5)^24 | AC4: =$B4*(1-Inputs!$B$5)^25 | AD4: =$B4*(1-Inputs!$B$5)^26 | AE4: =$B4*(1-Inputs!$B$5)^27 | AF4: =$B4*(1-Inputs!$B$5)^28 | AG4: =$B4*(1-Inputs!$B$5)^29 | AH4: =$B4*(1-Inputs!$B$5)^30 | AI4: =$B4*(1-Inputs!$B$5)^31 | AJ4: =$B4*(1-Inputs!$B$5)^32 | AK4: =$B4*(1-Inputs!$B$5)^33 | AL4: =$B4*(1-Inputs!$B$5)^34
A5: 3 | B5: =Inputs!$B$4 | C5: =0 | D5: =0 | E5: =$B5*(1-Inputs!$B$5)^0 | F5: =$B5*(1-Inputs!$B$5)^1 | G5: =$B5*(1-Inputs!$B$5)^2 | H5: =$B5*(1-Inputs!$B$5)^3 | I5: =$B5*(1-Inputs!$B$5)^4 | J5: =$B5*(1-Inputs!$B$5)^5 | K5: =$B5*(1-Inputs!$B$5)^6 | L5: =$B5*(1-Inputs!$B$5)^7 | M5: =$B5*(1-Inputs!$B$5)^8 | N5: =$B5*(1-Inputs!$B$5)^9 | O5: =$B5*(1-Inputs!$B$5)^10 | P5: =$B5*(1-Inputs!$B$5)^11 | Q5: =$B5*(1-Inputs!$B$5)^12 | R5: =$B5*(1-Inputs!$B$5)^13 | S5: =$B5*(1-Inputs!$B$5)^14 | T5: =$B5*(1-Inputs!$B$5)^15 | U5: =$B5*(1-Inputs!$B$5)^16 | V5: =$B5*(1-Inputs!$B$5)^17 | W5: =$B5*(1-Inputs!$B$5)^18 | X5: =$B5*(1-Inputs!$B$5)^19 | Y5: =$B5*(1-Inputs!$B$5)^20 | Z5: =$B5*(1-Inputs!$B$5)^21 | AA5: =$B5*(1-Inputs!$B$5)^22 | AB5: =$B5*(1-Inputs!$B$5)^23 | AC5: =$B5*(1-Inputs!$B$5)^24 | AD5: =$B5*(1-Inputs!$B$5)^25 | AE5: =$B5*(1-Inputs!$B$5)^26 | AF5: =$B5*(1-Inputs!$B$5)^27 | AG5: =$B5*(1-Inputs!$B$5)^28 | AH5: =$B5*(1-Inputs!$B$5)^29 | AI5: =$B5*(1-Inputs!$B$5)^30 | AJ5: =$B5*(1-Inputs!$B$5)^31 | AK5: =$B5*(1-Inputs!$B$5)^32 | AL5: =$B5*(1-Inputs!$B$5)^33
A6: 4 | B6: =Inputs!$B$4 | C6: =0 | D6: =0 | E6: =0 | F6: =$B6*(1-Inputs!$B$5)^0 | G6: =$B6*(1-Inputs!$B$5)^1 | H6: =$B6*(1-Inputs!$B$5)^2 | I6: =$B6*(1-Inputs!$B$5)^3 | J6: =$B6*(1-Inputs!$B$5)^4 | K6: =$B6*(1-Inputs!$B$5)^5 | L6: =$B6*(1-Inputs!$B$5)^6 | M6: =$B6*(1-Inputs!$B$5)^7 | N6: =$B6*(1-Inputs!$B$5)^8 | O6: =$B6*(1-Inputs!$B$5)^9 | P6: =$B6*(1-Inputs!$B$5)^10 | Q6: =$B6*(1-Inputs!$B$5)^11 | R6: =$B6*(1-Inputs!$B$5)^12 | S6: =$B6*(1-Inputs!$B$5)^13 | T6: =$B6*(1-Inputs!$B$5)^14 | U6: =$B6*(1-Inputs!$B$5)^15 | V6: =$B6*(1-Inputs!$B$5)^16 | W6: =$B6*(1-Inputs!$B$5)^17 | X6: =$B6*(1-Inputs!$B$5)^18 | Y6: =$B6*(1-Inputs!$B$5)^19 | Z6: =$B6*(1-Inputs!$B$5)^20 | AA6: =$B6*(1-Inputs!$B$5)^21 | AB6: =$B6*(1-Inputs!$B$5)^22 | AC6: =$B6*(1-Inputs!$B$5)^23 | AD6: =$B6*(1-Inputs!$B$5)^24 | AE6: =$B6*(1-Inputs!$B$5)^25 | AF6: =$B6*(1-Inputs!$B$5)^26 | AG6: =$B6*(1-Inputs!$B$5)^27 | AH6: =$B6*(1-Inputs!$B$5)^28 | AI6: =$B6*(1-Inputs!$B$5)^29 | AJ6: =$B6*(1-Inputs!$B$5)^30 | AK6: =$B6*(1-Inputs!$B$5)^31 | AL6: =$B6*(1-Inputs!$B$5)^32
A7: 5 | B7: =Inputs!$B$4 | C7: =0 | D7: =0 | E7: =0 | F7: =0 | G7: =$B7*(1-Inputs!$B$5)^0 | H7: =$B7*(1-Inputs!$B$5)^1 | I7: =$B7*(1-Inputs!$B$5)^2 | J7: =$B7*(1-Inputs!$B$5)^3 | K7: =$B7*(1-Inputs!$B$5)^4 | L7: =$B7*(1-Inputs!$B$5)^5 | M7: =$B7*(1-Inputs!$B$5)^6 | N7: =$B7*(1-Inputs!$B$5)^7 | O7: =$B7*(1-Inputs!$B$5)^8 | P7: =$B7*(1-Inputs!$B$5)^9 | Q7: =$B7*(1-Inputs!$B$5)^10 | R7: =$B7*(1-Inputs!$B$5)^11 | S7: =$B7*(1-Inputs!$B$5)^12 | T7: =$B7*(1-Inputs!$B$5)^13 | U7: =$B7*(1-Inputs!$B$5)^14 | V7: =$B7*(1-Inputs!$B$5)^15 | W7: =$B7*(1-Inputs!$B$5)^16 | X7: =$B7*(1-Inputs!$B$5)^17 | Y7: =$B7*(1-Inputs!$B$5)^18 | Z7: =$B7*(1-Inputs!$B$5)^19 | AA7: =$B7*(1-Inputs!$B$5)^20 | AB7: =$B7*(1-Inputs!$B$5)^21 | AC7: =$B7*(1-Inputs!$B$5)^22 | AD7: =$B7*(1-Inputs!$B$5)^23 | AE7: =$B7*(1-Inputs!$B$5)^24 | AF7: =$B7*(1-Inputs!$B$5)^25 | AG7: =$B7*(1-Inputs!$B$5)^26 | AH7: =$B7*(1-Inputs!$B$5)^27 | AI7: =$B7*(1-Inputs!$B$5)^28 | AJ7: =$B7*(1-Inputs!$B$5)^29 | AK7: =$B7*(1-Inputs!$B$5)^30 | AL7: =$B7*(1-Inputs!$B$5)^31
A8: 6 | B8: =Inputs!$B$4 | C8: =0 | D8: =0 | E8: =0 | F8: =0 | G8: =0 | H8: =$B8*(1-Inputs!$B$5)^0 | I8: =$B8*(1-Inputs!$B$5)^1 | J8: =$B8*(1-Inputs!$B$5)^2 | K8: =$B8*(1-Inputs!$B$5)^3 | L8: =$B8*(1-Inputs!$B$5)^4 | M8: =$B8*(1-Inputs!$B$5)^5 | N8: =$B8*(1-Inputs!$B$5)^6 | O8: =$B8*(1-Inputs!$B$5)^7 | P8: =$B8*(1-Inputs!$B$5)^8 | Q8: =$B8*(1-Inputs!$B$5)^9 | R8: =$B8*(1-Inputs!$B$5)^10 | S8: =$B8*(1-Inputs!$B$5)^11 | T8: =$B8*(1-Inputs!$B$5)^12 | U8: =$B8*(1-Inputs!$B$5)^13 | V8: =$B8*(1-Inputs!$B$5)^14 | W8: =$B8*(1-Inputs!$B$5)^15 | X8: =$B8*(1-Inputs!$B$5)^16 | Y8: =$B8*(1-Inputs!$B$5)^17 | Z8: =$B8*(1-Inputs!$B$5)^18 | AA8: =$B8*(1-Inputs!$B$5)^19 | AB8: =$B8*(1-Inputs!$B$5)^20 | AC8: =$B8*(1-Inputs!$B$5)^21 | AD8: =$B8*(1-Inputs!$B$5)^22 | AE8: =$B8*(1-Inputs!$B$5)^23 | AF8: =$B8*(1-Inputs!$B$5)^24 | AG8: =$B8*(1-Inputs!$B$5)^25 | AH8: =$B8*(1-Inputs!$B$5)^26 | AI8: =$B8*(1-Inputs!$B$5)^27 | AJ8: =$B8*(1-Inputs!$B$5)^28 | AK8: =$B8*(1-Inputs!$B$5)^29 | AL8: =$B8*(1-Inputs!$B$5)^30
A9: 7 | B9: =Inputs!$B$4 | C9: =0 | D9: =0 | E9: =0 | F9: =0 | G9: =0 | H9: =0 | I9: =$B9*(1-Inputs!$B$5)^0 | J9: =$B9*(1-Inputs!$B$5)^1 | K9: =$B9*(1-Inputs!$B$5)^2 | L9: =$B9*(1-Inputs!$B$5)^3 | M9: =$B9*(1-Inputs!$B$5)^4 | N9: =$B9*(1-Inputs!$B$5)^5 | O9: =$B9*(1-Inputs!$B$5)^6 | P9: =$B9*(1-Inputs!$B$5)^7 | Q9: =$B9*(1-Inputs!$B$5)^8 | R9: =$B9*(1-Inputs!$B$5)^9 | S9: =$B9*(1-Inputs!$B$5)^10 | T9: =$B9*(1-Inputs!$B$5)^11 | U9: =$B9*(1-Inputs!$B$5)^12 | V9: =$B9*(1-Inputs!$B$5)^13 | W9: =$B9*(1-Inputs!$B$5)^14 | X9: =$B9*(1-Inputs!$B$5)^15 | Y9: =$B9*(1-Inputs!$B$5)^16 | Z9: =$B9*(1-Inputs!$B$5)^17 | AA9: =$B9*(1-Inputs!$B$5)^18 | AB9: =$B9*(1-Inputs!$B$5)^19 | AC9: =$B9*(1-Inputs!$B$5)^20 | AD9: =$B9*(1-Inputs!$B$5)^21 | AE9: =$B9*(1-Inputs!$B$5)^22 | AF9: =$B9*(1-Inputs!$B$5)^23 | AG9: =$B9*(1-Inputs!$B$5)^24 | AH9: =$B9*(1-Inputs!$B$5)^25 | AI9: =$B9*(1-Inputs!$B$5)^26 | AJ9: =$B9*(1-Inputs!$B$5)^27 | AK9: =$B9*(1-Inputs!$B$5)^28 | AL9: =$B9*(1-Inputs!$B$5)^29
A10: 8 | B10: =Inputs!$B$4 | C10: =0 | D10: =0 | E10: =0 | F10: =0 | G10: =0 | H10: =0 | I10: =0 | J10: =$B10*(1-Inputs!$B$5)^0 | K10: =$B10*(1-Inputs!$B$5)^1 | L10: =$B10*(1-Inputs!$B$5)^2 | M10: =$B10*(1-Inputs!$B$5)^3 | N10: =$B10*(1-Inputs!$B$5)^4 | O10: =$B10*(1-Inputs!$B$5)^5 | P10: =$B10*(1-Inputs!$B$5)^6 | Q10: =$B10*(1-Inputs!$B$5)^7 | R10: =$B10*(1-Inputs!$B$5)^8 | S10: =$B10*(1-Inputs!$B$5)^9 | T10: =$B10*(1-Inputs!$B$5)^10 | U10: =$B10*(1-Inputs!$B$5)^11 | V10: =$B10*(1-Inputs!$B$5)^12 | W10: =$B10*(1-Inputs!$B$5)^13 | X10: =$B10*(1-Inputs!$B$5)^14 | Y10: =$B10*(1-Inputs!$B$5)^15 | Z10: =$B10*(1-Inputs!$B$5)^16 | AA10: =$B10*(1-Inputs!$B$5)^17 | AB10: =$B10*(1-Inputs!$B$5)^18 | AC10: =$B10*(1-Inputs!$B$5)^19 | AD10: =$B10*(1-Inputs!$B$5)^20 | AE10: =$B10*(1-Inputs!$B$5)^21 | AF10: =$B10*(1-Inputs!$B$5)^22 | AG10: =$B10*(1-Inputs!$B$5)^23 | AH10: =$B10*(1-Inputs!$B$5)^24 | AI10: =$B10*(1-Inputs!$B$5)^25 | AJ10: =$B10*(1-Inputs!$B$5)^26 | AK10: =$B10*(1-Inputs!$B$5)^27 | AL10: =$B10*(1-Inputs!$B$5)^28
A11: 9 | B11: =Inputs!$B$4 | C11: =0 | D11: =0 | E11: =0 | F11: =0 | G11: =0 | H11: =0 | I11: =0 | J11: =0 | K11: =$B11*(1-Inputs!$B$5)^0 | L11: =$B11*(1-Inputs!$B$5)^1 | M11: =$B11*(1-Inputs!$B$5)^2 | N11: =$B11*(1-Inputs!$B$5)^3 | O11: =$B11*(1-Inputs!$B$5)^4 | P11: =$B11*(1-Inputs!$B$5)^5 | Q11: =$B11*(1-Inputs!$B$5)^6 | R11: =$B11*(1-Inputs!$B$5)^7 | S11: =$B11*(1-Inputs!$B$5)^8 | T11: =$B11*(1-Inputs!$B$5)^9 | U11: =$B11*(1-Inputs!$B$5)^10 | V11: =$B11*(1-Inputs!$B$5)^11 | W11: =$B11*(1-Inputs!$B$5)^12 | X11: =$B11*(1-Inputs!$B$5)^13 | Y11: =$B11*(1-Inputs!$B$5)^14 | Z11: =$B11*(1-Inputs!$B$5)^15 | AA11: =$B11*(1-Inputs!$B$5)^16 | AB11: =$B11*(1-Inputs!$B$5)^17 | AC11: =$B11*(1-Inputs!$B$5)^18 | AD11: =$B11*(1-Inputs!$B$5)^19 | AE11: =$B11*(1-Inputs!$B$5)^20 | AF11: =$B11*(1-Inputs!$B$5)^21 | AG11: =$B11*(1-Inputs!$B$5)^22 | AH11: =$B11*(1-Inputs!$B$5)^23 | AI11: =$B11*(1-Inputs!$B$5)^24 | AJ11: =$B11*(1-Inputs!$B$5)^25 | AK11: =$B11*(1-Inputs!$B$5)^26 | AL11: =$B11*(1-Inputs!$B$5)^27
A12: 10 | B12: =Inputs!$B$4 | C12: =0 | D12: =0 | E12: =0 | F12: =0 | G12: =0 | H12: =0 | I12: =0 | J12: =0 | K12: =0 | L12: =$B12*(1-Inputs!$B$5)^0 | M12: =$B12*(1-Inputs!$B$5)^1 | N12: =$B12*(1-Inputs!$B$5)^2 | O12: =$B12*(1-Inputs!$B$5)^3 | P12: =$B12*(1-Inputs!$B$5)^4 | Q12: =$B12*(1-Inputs!$B$5)^5 | R12: =$B12*(1-Inputs!$B$5)^6 | S12: =$B12*(1-Inputs!$B$5)^7 | T12: =$B12*(1-Inputs!$B$5)^8 | U12: =$B12*(1-Inputs!$B$5)^9 | V12: =$B12*(1-Inputs!$B$5)^10 | W12: =$B12*(1-Inputs!$B$5)^11 | X12: =$B12*(1-Inputs!$B$5)^12 | Y12: =$B12*(1-Inputs!$B$5)^13 | Z12: =$B12*(1-Inputs!$B$5)^14 | AA12: =$B12*(1-Inputs!$B$5)^15 | AB12: =$B12*(1-Inputs!$B$5)^16 | AC12: =$B12*(1-Inputs!$B$5)^17 | AD12: =$B12*(1-Inputs!$B$5)^18 | AE12: =$B12*(1-Inputs!$B$5)^19 | AF12: =$B12*(1-Inputs!$B$5)^20 | AG12: =$B12*(1-Inputs!$B$5)^21 | AH12: =$B12*(1-Inputs!$B$5)^22 | AI12: =$B12*(1-Inputs!$B$5)^23 | AJ12: =$B12*(1-Inputs!$B$5)^24 | AK12: =$B12*(1-Inputs!$B$5)^25 | AL12: =$B12*(1-Inputs!$B$5)^26
A13: 11 | B13: =Inputs!$B$4 | C13: =0 | D13: =0 | E13: =0 | F13: =0 | G13: =0 | H13: =0 | I13: =0 | J13: =0 | ... L13: =0 | M13: =$B13*(1-Inputs!$B$5)^0 | N13: =$B13*(1-Inputs!$B$5)^1 | O13: =$B13*(1-Inputs!$B$5)^2 | P13: =$B13*(1-Inputs!$B$5)^3 | Q13: =$B13*(1-Inputs!$B$5)^4 | R13: =$B13*(1-Inputs!$B$5)^5 | S13: =$B13*(1-Inputs!$B$5)^6 | T13: =$B13*(1-Inputs!$B$5)^7 | U13: =$B13*(1-Inputs!$B$5)^8 | V13: =$B13*(1-Inputs!$B$5)^9 | W13: =$B13*(1-Inputs!$B$5)^10 | X13: =$B13*(1-Inputs!$B$5)^11 | Y13: =$B13*(1-Inputs!$B$5)^12 | Z13: =$B13*(1-Inputs!$B$5)^13 | AA13: =$B13*(1-Inputs!$B$5)^14 | AB13: =$B13*(1-Inputs!$B$5)^15 | AC13: =$B13*(1-Inputs!$B$5)^16 | AD13: =$B13*(1-Inputs!$B$5)^17 | AE13: =$B13*(1-Inputs!$B$5)^18 | AF13: =$B13*(1-Inputs!$B$5)^19 | AG13: =$B13*(1-Inputs!$B$5)^20 | AH13: =$B13*(1-Inputs!$B$5)^21 | AI13: =$B13*(1-Inputs!$B$5)^22 | AJ13: =$B13*(1-Inputs!$B$5)^23 | AK13: =$B13*(1-Inputs!$B$5)^24 | AL13: =$B13*(1-Inputs!$B$5)^25
A14: 12 | B14: =Inputs!$B$4 | C14: =0 | D14: =0 | E14: =0 | F14: =0 | G14: =0 | H14: =0 | I14: =0 | J14: =0 | ... M14: =0 | N14: =$B14*(1-Inputs!$B$5)^0 | O14: =$B14*(1-Inputs!$B$5)^1 | P14: =$B14*(1-Inputs!$B$5)^2 | Q14: =$B14*(1-Inputs!$B$5)^3 | R14: =$B14*(1-Inputs!$B$5)^4 | S14: =$B14*(1-Inputs!$B$5)^5 | T14: =$B14*(1-Inputs!$B$5)^6 | U14: =$B14*(1-Inputs!$B$5)^7 | V14: =$B14*(1-Inputs!$B$5)^8 | W14: =$B14*(1-Inputs!$B$5)^9 | X14: =$B14*(1-Inputs!$B$5)^10 | Y14: =$B14*(1-Inputs!$B$5)^11 | Z14: =$B14*(1-Inputs!$B$5)^12 | AA14: =$B14*(1-Inputs!$B$5)^13 | AB14: =$B14*(1-Inputs!$B$5)^14 | AC14: =$B14*(1-Inputs!$B$5)^15 | AD14: =$B14*(1-Inputs!$B$5)^16 | AE14: =$B14*(1-Inputs!$B$5)^17 | AF14: =$B14*(1-Inputs!$B$5)^18 | AG14: =$B14*(1-Inputs!$B$5)^19 | AH14: =$B14*(1-Inputs!$B$5)^20 | AI14: =$B14*(1-Inputs!$B$5)^21 | AJ14: =$B14*(1-Inputs!$B$5)^22 | AK14: =$B14*(1-Inputs!$B$5)^23 | AL14: =$B14*(1-Inputs!$B$5)^24
A15: 13 | B15: =Inputs!$B$4 | C15: =0 | D15: =0 | E15: =0 | F15: =0 | G15: =0 | H15: =0 | I15: =0 | J15: =0 | ... N15: =0 | O15: =$B15*(1-Inputs!$B$5)^0 | P15: =$B15*(1-Inputs!$B$5)^1 | Q15: =$B15*(1-Inputs!$B$5)^2 | R15: =$B15*(1-Inputs!$B$5)^3 | S15: =$B15*(1-Inputs!$B$5)^4 | T15: =$B15*(1-Inputs!$B$5)^5 | U15: =$B15*(1-Inputs!$B$5)^6 | V15: =$B15*(1-Inputs!$B$5)^7 | W15: =$B15*(1-Inputs!$B$5)^8 | X15: =$B15*(1-Inputs!$B$5)^9 | Y15: =$B15*(1-Inputs!$B$5)^10 | Z15: =$B15*(1-Inputs!$B$5)^11 | AA15: =$B15*(1-Inputs!$B$5)^12 | AB15: =$B15*(1-Inputs!$B$5)^13 | AC15: =$B15*(1-Inputs!$B$5)^14 | AD15: =$B15*(1-Inputs!$B$5)^15 | AE15: =$B15*(1-Inputs!$B$5)^16 | AF15: =$B15*(1-Inputs!$B$5)^17 | AG15: =$B15*(1-Inputs!$B$5)^18 | AH15: =$B15*(1-Inputs!$B$5)^19 | AI15: =$B15*(1-Inputs!$B$5)^20 | AJ15: =$B15*(1-Inputs!$B$5)^21 | AK15: =$B15*(1-Inputs!$B$5)^22 | AL15: =$B15*(1-Inputs!$B$5)^23
A16: 14 | B16: =Inputs!$B$4 | C16: =0 | D16: =0 | E16: =0 | F16: =0 | G16: =0 | H16: =0 | I16: =0 | J16: =0 | ... O16: =0 | P16: =$B16*(1-Inputs!$B$5)^0 | Q16: =$B16*(1-Inputs!$B$5)^1 | R16: =$B16*(1-Inputs!$B$5)^2 | S16: =$B16*(1-Inputs!$B$5)^3 | T16: =$B16*(1-Inputs!$B$5)^4 | U16: =$B16*(1-Inputs!$B$5)^5 | V16: =$B16*(1-Inputs!$B$5)^6 | W16: =$B16*(1-Inputs!$B$5)^7 | X16: =$B16*(1-Inputs!$B$5)^8 | Y16: =$B16*(1-Inputs!$B$5)^9 | Z16: =$B16*(1-Inputs!$B$5)^10 | AA16: =$B16*(1-Inputs!$B$5)^11 | AB16: =$B16*(1-Inputs!$B$5)^12 | AC16: =$B16*(1-Inputs!$B$5)^13 | AD16: =$B16*(1-Inputs!$B$5)^14 | AE16: =$B16*(1-Inputs!$B$5)^15 | AF16: =$B16*(1-Inputs!$B$5)^16 | AG16: =$B16*(1-Inputs!$B$5)^17 | AH16: =$B16*(1-Inputs!$B$5)^18 | AI16: =$B16*(1-Inputs!$B$5)^19 | AJ16: =$B16*(1-Inputs!$B$5)^20 | AK16: =$B16*(1-Inputs!$B$5)^21 | AL16: =$B16*(1-Inputs!$B$5)^22
A17: 15 | B17: =Inputs!$B$4 | C17: =0 | D17: =0 | E17: =0 | F17: =0 | G17: =0 | H17: =0 | I17: =0 | J17: =0 | ... P17: =0 | Q17: =$B17*(1-Inputs!$B$5)^0 | R17: =$B17*(1-Inputs!$B$5)^1 | S17: =$B17*(1-Inputs!$B$5)^2 | T17: =$B17*(1-Inputs!$B$5)^3 | U17: =$B17*(1-Inputs!$B$5)^4 | V17: =$B17*(1-Inputs!$B$5)^5 | W17: =$B17*(1-Inputs!$B$5)^6 | X17: =$B17*(1-Inputs!$B$5)^7 | Y17: =$B17*(1-Inputs!$B$5)^8 | Z17: =$B17*(1-Inputs!$B$5)^9 | AA17: =$B17*(1-Inputs!$B$5)^10 | AB17: =$B17*(1-Inputs!$B$5)^11 | AC17: =$B17*(1-Inputs!$B$5)^12 | AD17: =$B17*(1-Inputs!$B$5)^13 | AE17: =$B17*(1-Inputs!$B$5)^14 | AF17: =$B17*(1-Inputs!$B$5)^15 | AG17: =$B17*(1-Inputs!$B$5)^16 | AH17: =$B17*(1-Inputs!$B$5)^17 | AI17: =$B17*(1-Inputs!$B$5)^18 | AJ17: =$B17*(1-Inputs!$B$5)^19 | AK17: =$B17*(1-Inputs!$B$5)^20 | AL17: =$B17*(1-Inputs!$B$5)^21
A18: 16 | B18: =Inputs!$B$4 | C18: =0 | D18: =0 | E18: =0 | F18: =0 | G18: =0 | H18: =0 | I18: =0 | J18: =0 | ... Q18: =0 | R18: =$B18*(1-Inputs!$B$5)^0 | S18: =$B18*(1-Inputs!$B$5)^1 | T18: =$B18*(1-Inputs!$B$5)^2 | U18: =$B18*(1-Inputs!$B$5)^3 | V18: =$B18*(1-Inputs!$B$5)^4 | W18: =$B18*(1-Inputs!$B$5)^5 | X18: =$B18*(1-Inputs!$B$5)^6 | Y18: =$B18*(1-Inputs!$B$5)^7 | Z18: =$B18*(1-Inputs!$B$5)^8 | AA18: =$B18*(1-Inputs!$B$5)^9 | AB18: =$B18*(1-Inputs!$B$5)^10 | AC18: =$B18*(1-Inputs!$B$5)^11 | AD18: =$B18*(1-Inputs!$B$5)^12 | AE18: =$B18*(1-Inputs!$B$5)^13 | AF18: =$B18*(1-Inputs!$B$5)^14 | AG18: =$B18*(1-Inputs!$B$5)^15 | AH18: =$B18*(1-Inputs!$B$5)^16 | AI18: =$B18*(1-Inputs!$B$5)^17 | AJ18: =$B18*(1-Inputs!$B$5)^18 | AK18: =$B18*(1-Inputs!$B$5)^19 | AL18: =$B18*(1-Inputs!$B$5)^20
A19: 17 | B19: =Inputs!$B$4 | C19: =0 | D19: =0 | E19: =0 | F19: =0 | G19: =0 | H19: =0 | I19: =0 | J19: =0 | ... R19: =0 | S19: =$B19*(1-Inputs!$B$5)^0 | T19: =$B19*(1-Inputs!$B$5)^1 | U19: =$B19*(1-Inputs!$B$5)^2 | V19: =$B19*(1-Inputs!$B$5)^3 | W19: =$B19*(1-Inputs!$B$5)^4 | X19: =$B19*(1-Inputs!$B$5)^5 | Y19: =$B19*(1-Inputs!$B$5)^6 | Z19: =$B19*(1-Inputs!$B$5)^7 | AA19: =$B19*(1-Inputs!$B$5)^8 | AB19: =$B19*(1-Inputs!$B$5)^9 | AC19: =$B19*(1-Inputs!$B$5)^10 | AD19: =$B19*(1-Inputs!$B$5)^11 | AE19: =$B19*(1-Inputs!$B$5)^12 | AF19: =$B19*(1-Inputs!$B$5)^13 | AG19: =$B19*(1-Inputs!$B$5)^14 | AH19: =$B19*(1-Inputs!$B$5)^15 | AI19: =$B19*(1-Inputs!$B$5)^16 | AJ19: =$B19*(1-Inputs!$B$5)^17 | AK19: =$B19*(1-Inputs!$B$5)^18 | AL19: =$B19*(1-Inputs!$B$5)^19
A20: 18 | B20: =Inputs!$B$4 | C20: =0 | D20: =0 | E20: =0 | F20: =0 | G20: =0 | H20: =0 | I20: =0 | J20: =0 | ... S20: =0 | T20: =$B20*(1-Inputs!$B$5)^0 | U20: =$B20*(1-Inputs!$B$5)^1 | V20: =$B20*(1-Inputs!$B$5)^2 | W20: =$B20*(1-Inputs!$B$5)^3 | X20: =$B20*(1-Inputs!$B$5)^4 | Y20: =$B20*(1-Inputs!$B$5)^5 | Z20: =$B20*(1-Inputs!$B$5)^6 | AA20: =$B20*(1-Inputs!$B$5)^7 | AB20: =$B20*(1-Inputs!$B$5)^8 | AC20: =$B20*(1-Inputs!$B$5)^9 | AD20: =$B20*(1-Inputs!$B$5)^10 | AE20: =$B20*(1-Inputs!$B$5)^11 | AF20: =$B20*(1-Inputs!$B$5)^12 | AG20: =$B20*(1-Inputs!$B$5)^13 | AH20: =$B20*(1-Inputs!$B$5)^14 | AI20: =$B20*(1-Inputs!$B$5)^15 | AJ20: =$B20*(1-Inputs!$B$5)^16 | AK20: =$B20*(1-Inputs!$B$5)^17 | AL20: =$B20*(1-Inputs!$B$5)^18
A21: 19 | B21: =Inputs!$B$4 | C21: =0 | D21: =0 | E21: =0 | F21: =0 | G21: =0 | H21: =0 | I21: =0 | J21: =0 | ... T21: =0 | U21: =$B21*(1-Inputs!$B$5)^0 | V21: =$B21*(1-Inputs!$B$5)^1 | W21: =$B21*(1-Inputs!$B$5)^2 | X21: =$B21*(1-Inputs!$B$5)^3 | Y21: =$B21*(1-Inputs!$B$5)^4 | Z21: =$B21*(1-Inputs!$B$5)^5 | AA21: =$B21*(1-Inputs!$B$5)^6 | AB21: =$B21*(1-Inputs!$B$5)^7 | AC21: =$B21*(1-Inputs!$B$5)^8 | AD21: =$B21*(1-Inputs!$B$5)^9 | AE21: =$B21*(1-Inputs!$B$5)^10 | AF21: =$B21*(1-Inputs!$B$5)^11 | AG21: =$B21*(1-Inputs!$B$5)^12 | AH21: =$B21*(1-Inputs!$B$5)^13 | AI21: =$B21*(1-Inputs!$B$5)^14 | AJ21: =$B21*(1-Inputs!$B$5)^15 | AK21: =$B21*(1-Inputs!$B$5)^16 | AL21: =$B21*(1-Inputs!$B$5)^17
A22: 20 | B22: =Inputs!$B$4 | C22: =0 | D22: =0 | E22: =0 | F22: =0 | G22: =0 | H22: =0 | I22: =0 | J22: =0 | ... U22: =0 | V22: =$B22*(1-Inputs!$B$5)^0 | W22: =$B22*(1-Inputs!$B$5)^1 | X22: =$B22*(1-Inputs!$B$5)^2 | Y22: =$B22*(1-Inputs!$B$5)^3 | Z22: =$B22*(1-Inputs!$B$5)^4 | AA22: =$B22*(1-Inputs!$B$5)^5 | AB22: =$B22*(1-Inputs!$B$5)^6 | AC22: =$B22*(1-Inputs!$B$5)^7 | AD22: =$B22*(1-Inputs!$B$5)^8 | AE22: =$B22*(1-Inputs!$B$5)^9 | AF22: =$B22*(1-Inputs!$B$5)^10 | AG22: =$B22*(1-Inputs!$B$5)^11 | AH22: =$B22*(1-Inputs!$B$5)^12 | AI22: =$B22*(1-Inputs!$B$5)^13 | AJ22: =$B22*(1-Inputs!$B$5)^14 | AK22: =$B22*(1-Inputs!$B$5)^15 | AL22: =$B22*(1-Inputs!$B$5)^16
A23: 21 | B23: =Inputs!$B$4 | C23: =0 | D23: =0 | E23: =0 | F23: =0 | G23: =0 | H23: =0 | I23: =0 | J23: =0 | ... V23: =0 | W23: =$B23*(1-Inputs!$B$5)^0 | X23: =$B23*(1-Inputs!$B$5)^1 | Y23: =$B23*(1-Inputs!$B$5)^2 | Z23: =$B23*(1-Inputs!$B$5)^3 | AA23: =$B23*(1-Inputs!$B$5)^4 | AB23: =$B23*(1-Inputs!$B$5)^5 | AC23: =$B23*(1-Inputs!$B$5)^6 | AD23: =$B23*(1-Inputs!$B$5)^7 | AE23: =$B23*(1-Inputs!$B$5)^8 | AF23: =$B23*(1-Inputs!$B$5)^9 | AG23: =$B23*(1-Inputs!$B$5)^10 | AH23: =$B23*(1-Inputs!$B$5)^11 | AI23: =$B23*(1-Inputs!$B$5)^12 | AJ23: =$B23*(1-Inputs!$B$5)^13 | AK23: =$B23*(1-Inputs!$B$5)^14 | AL23: =$B23*(1-Inputs!$B$5)^15
A24: 22 | B24: =Inputs!$B$4 | C24: =0 | D24: =0 | E24: =0 | F24: =0 | G24: =0 | H24: =0 | I24: =0 | J24: =0 | ... W24: =0 | X24: =$B24*(1-Inputs!$B$5)^0 | Y24: =$B24*(1-Inputs!$B$5)^1 | Z24: =$B24*(1-Inputs!$B$5)^2 | AA24: =$B24*(1-Inputs!$B$5)^3 | AB24: =$B24*(1-Inputs!$B$5)^4 | AC24: =$B24*(1-Inputs!$B$5)^5 | AD24: =$B24*(1-Inputs!$B$5)^6 | AE24: =$B24*(1-Inputs!$B$5)^7 | AF24: =$B24*(1-Inputs!$B$5)^8 | AG24: =$B24*(1-Inputs!$B$5)^9 | AH24: =$B24*(1-Inputs!$B$5)^10 | AI24: =$B24*(1-Inputs!$B$5)^11 | AJ24: =$B24*(1-Inputs!$B$5)^12 | AK24: =$B24*(1-Inputs!$B$5)^13 | AL24: =$B24*(1-Inputs!$B$5)^14
A25: 23 | B25: =Inputs!$B$4 | C25: =0 | D25: =0 | E25: =0 | F25: =0 | G25: =0 | H25: =0 | I25: =0 | J25: =0 | ... X25: =0 | Y25: =$B25*(1-Inputs!$B$5)^0 | Z25: =$B25*(1-Inputs!$B$5)^1 | AA25: =$B25*(1-Inputs!$B$5)^2 | AB25: =$B25*(1-Inputs!$B$5)^3 | AC25: =$B25*(1-Inputs!$B$5)^4 | AD25: =$B25*(1-Inputs!$B$5)^5 | AE25: =$B25*(1-Inputs!$B$5)^6 | AF25: =$B25*(1-Inputs!$B$5)^7 | AG25: =$B25*(1-Inputs!$B$5)^8 | AH25: =$B25*(1-Inputs!$B$5)^9 | AI25: =$B25*(1-Inputs!$B$5)^10 | AJ25: =$B25*(1-Inputs!$B$5)^11 | AK25: =$B25*(1-Inputs!$B$5)^12 | AL25: =$B25*(1-Inputs!$B$5)^13
A26: 24 | B26: =Inputs!$B$4 | C26: =0 | D26: =0 | E26: =0 | F26: =0 | G26: =0 | H26: =0 | I26: =0 | J26: =0 | ... Y26: =0 | Z26: =$B26*(1-Inputs!$B$5)^0 | AA26: =$B26*(1-Inputs!$B$5)^1 | AB26: =$B26*(1-Inputs!$B$5)^2 | AC26: =$B26*(1-Inputs!$B$5)^3 | AD26: =$B26*(1-Inputs!$B$5)^4 | AE26: =$B26*(1-Inputs!$B$5)^5 | AF26: =$B26*(1-Inputs!$B$5)^6 | AG26: =$B26*(1-Inputs!$B$5)^7 | AH26: =$B26*(1-Inputs!$B$5)^8 | AI26: =$B26*(1-Inputs!$B$5)^9 | AJ26: =$B26*(1-Inputs!$B$5)^10 | AK26: =$B26*(1-Inputs!$B$5)^11 | AL26: =$B26*(1-Inputs!$B$5)^12
A27: 25 | B27: =Inputs!$B$4 | C27: =0 | D27: =0 | E27: =0 | F27: =0 | G27: =0 | H27: =0 | I27: =0 | J27: =0 | ... Z27: =0 | AA27: =$B27*(1-Inputs!$B$5)^0 | AB27: =$B27*(1-Inputs!$B$5)^1 | AC27: =$B27*(1-Inputs!$B$5)^2 | AD27: =$B27*(1-Inputs!$B$5)^3 | AE27: =$B27*(1-Inputs!$B$5)^4 | AF27: =$B27*(1-Inputs!$B$5)^5 | AG27: =$B27*(1-Inputs!$B$5)^6 | AH27: =$B27*(1-Inputs!$B$5)^7 | AI27: =$B27*(1-Inputs!$B$5)^8 | AJ27: =$B27*(1-Inputs!$B$5)^9 | AK27: =$B27*(1-Inputs!$B$5)^10 | AL27: =$B27*(1-Inputs!$B$5)^11
A28: 26 | B28: =Inputs!$B$4 | C28: =0 | D28: =0 | E28: =0 | F28: =0 | G28: =0 | H28: =0 | I28: =0 | J28: =0 | ... AA28: =0 | AB28: =$B28*(1-Inputs!$B$5)^0 | AC28: =$B28*(1-Inputs!$B$5)^1 | AD28: =$B28*(1-Inputs!$B$5)^2 | AE28: =$B28*(1-Inputs!$B$5)^3 | AF28: =$B28*(1-Inputs!$B$5)^4 | AG28: =$B28*(1-Inputs!$B$5)^5 | AH28: =$B28*(1-Inputs!$B$5)^6 | AI28: =$B28*(1-Inputs!$B$5)^7 | AJ28: =$B28*(1-Inputs!$B$5)^8 | AK28: =$B28*(1-Inputs!$B$5)^9 | AL28: =$B28*(1-Inputs!$B$5)^10
A29: 27 | B29: =Inputs!$B$4 | C29: =0 | D29: =0 | E29: =0 | F29: =0 | G29: =0 | H29: =0 | I29: =0 | J29: =0 | ... AB29: =0 | AC29: =$B29*(1-Inputs!$B$5)^0 | AD29: =$B29*(1-Inputs!$B$5)^1 | AE29: =$B29*(1-Inputs!$B$5)^2 | AF29: =$B29*(1-Inputs!$B$5)^3 | AG29: =$B29*(1-Inputs!$B$5)^4 | AH29: =$B29*(1-Inputs!$B$5)^5 | AI29: =$B29*(1-Inputs!$B$5)^6 | AJ29: =$B29*(1-Inputs!$B$5)^7 | AK29: =$B29*(1-Inputs!$B$5)^8 | AL29: =$B29*(1-Inputs!$B$5)^9
A30: 28 | B30: =Inputs!$B$4 | C30: =0 | D30: =0 | E30: =0 | F30: =0 | G30: =0 | H30: =0 | I30: =0 | J30: =0 | ... AC30: =0 | AD30: =$B30*(1-Inputs!$B$5)^0 | AE30: =$B30*(1-Inputs!$B$5)^1 | AF30: =$B30*(1-Inputs!$B$5)^2 | AG30: =$B30*(1-Inputs!$B$5)^3 | AH30: =$B30*(1-Inputs!$B$5)^4 | AI30: =$B30*(1-Inputs!$B$5)^5 | AJ30: =$B30*(1-Inputs!$B$5)^6 | AK30: =$B30*(1-Inputs!$B$5)^7 | AL30: =$B30*(1-Inputs!$B$5)^8
A31: 29 | B31: =Inputs!$B$4 | C31: =0 | D31: =0 | E31: =0 | F31: =0 | G31: =0 | H31: =0 | I31: =0 | J31: =0 | ... AD31: =0 | AE31: =$B31*(1-Inputs!$B$5)^0 | AF31: =$B31*(1-Inputs!$B$5)^1 | AG31: =$B31*(1-Inputs!$B$5)^2 | AH31: =$B31*(1-Inputs!$B$5)^3 | AI31: =$B31*(1-Inputs!$B$5)^4 | AJ31: =$B31*(1-Inputs!$B$5)^5 | AK31: =$B31*(1-Inputs!$B$5)^6 | AL31: =$B31*(1-Inputs!$B$5)^7
A32: 30 | B32: =Inputs!$B$4 | C32: =0 | D32: =0 | E32: =0 | F32: =0 | G32: =0 | H32: =0 | I32: =0 | J32: =0 | ... AE32: =0 | AF32: =$B32*(1-Inputs!$B$5)^0 | AG32: =$B32*(1-Inputs!$B$5)^1 | AH32: =$B32*(1-Inputs!$B$5)^2 | AI32: =$B32*(1-Inputs!$B$5)^3 | AJ32: =$B32*(1-Inputs!$B$5)^4 | AK32: =$B32*(1-Inputs!$B$5)^5 | AL32: =$B32*(1-Inputs!$B$5)^6
A33: 31 | B33: =Inputs!$B$4 | C33: =0 | D33: =0 | E33: =0 | F33: =0 | G33: =0 | H33: =0 | I33: =0 | J33: =0 | ... AF33: =0 | AG33: =$B33*(1-Inputs!$B$5)^0 | AH33: =$B33*(1-Inputs!$B$5)^1 | AI33: =$B33*(1-Inputs!$B$5)^2 | AJ33: =$B33*(1-Inputs!$B$5)^3 | AK33: =$B33*(1-Inputs!$B$5)^4 | AL33: =$B33*(1-Inputs!$B$5)^5
A34: 32 | B34: =Inputs!$B$4 | C34: =0 | D34: =0 | E34: =0 | F34: =0 | G34: =0 | H34: =0 | I34: =0 | J34: =0 | ... AG34: =0 | AH34: =$B34*(1-Inputs!$B$5)^0 | AI34: =$B34*(1-Inputs!$B$5)^1 | AJ34: =$B34*(1-Inputs!$B$5)^2 | AK34: =$B34*(1-Inputs!$B$5)^3 | AL34: =$B34*(1-Inputs!$B$5)^4
A35: 33 | B35: =Inputs!$B$4 | C35: =0 | D35: =0 | E35: =0 | F35: =0 | G35: =0 | H35: =0 | I35: =0 | J35: =0 | ... AH35: =0 | AI35: =$B35*(1-Inputs!$B$5)^0 | AJ35: =$B35*(1-Inputs!$B$5)^1 | AK35: =$B35*(1-Inputs!$B$5)^2 | AL35: =$B35*(1-Inputs!$B$5)^3
A36: 34 | B36: =Inputs!$B$4 | C36: =0 | D36: =0 | E36: =0 | F36: =0 | G36: =0 | H36: =0 | I36: =0 | J36: =0 | ... AI36: =0 | AJ36: =$B36*(1-Inputs!$B$5)^0 | AK36: =$B36*(1-Inputs!$B$5)^1 | AL36: =$B36*(1-Inputs!$B$5)^2
A37: 35 | B37: =Inputs!$B$4 | C37: =0 | D37: =0 | E37: =0 | F37: =0 | G37: =0 | H37: =0 | I37: =0 | J37: =0 | ... AJ37: =0 | AK37: =$B37*(1-Inputs!$B$5)^0 | AL37: =$B37*(1-Inputs!$B$5)^1
A38: 36 | B38: =Inputs!$B$4 | C38: =0 | D38: =0 | E38: =0 | F38: =0 | G38: =0 | H38: =0 | I38: =0 | J38: =0 | ... AK38: =0 | AL38: =$B38*(1-Inputs!$B$5)^0

Sheet Definitions
A1: All seeded amounts, rates, cohorts and thresholds are illustrative, not actual Semester results.
A2: 36 monthly expected-value periods; partner counts may be fractional.
A3: GMV uses average beginning/end active partners; new and exited partners approximately mid-period.
A4: Next Quarter means first three model months. Start defaults to November 2026; adjust to January 2027 for next calendar quarter.
A5: Net fees are transaction fee projections, not recognized accounting revenue or settled cash.
A6: ROI is program ROI from an assumed counterfactual; it is not demonstrated causal impact or partner-side ROI.
A7: Scenario changes are independent: no estimated demand elasticity from take-rate changes.
A8: Churn is partner exits / beginning cohort, not inactivity.
A9: Excel formulas are not evaluated in this environment; open in Excel to calculate.
A10: No live database link, alert delivery, deployment or migration was performed.
A11: Cost model excludes financing, taxes and working capital; add approved assumptions before financial decisions.
